{"format_version":"1.20.50","minecraft:item":{"description":{"identifier":"ftb_tc:cleaver_head_queens_slime_guard_ardite","menu_category":{"category":"equipment","group":"itemGroup.name.sword"}},"components":{"minecraft:max_stack_size":1,"minecraft:icon":{"texture":"tcl_q_slim_a35fc8"},"minecraft:display_name":{"value":"Queens Slime Cleaver\n\n§r§f§r§f §a4950\n§r§f§gSmeltery§r§f, §r§r§f§qBounce\n§9Tinkers' Construct"},"minecraft:enchantable":{"value":0,"slot":"sword"},"minecraft:damage":14,"minecraft:digger":{"use_efficiency":false,"destroy_speeds":[{"block":"minecraft:web","speed":28},{"block":"minecraft:bamboo","speed":28}]},"minecraft:tags":{"tags":["minecraft:is_sword"]},"minecraft:can_destroy_in_creative":false,"minecraft:hand_equipped":{"value":true},"minecraft:durability":{"max_durability":4950}}}}