{"format_version":"1.19.60","animation_controllers":{"controller.animation.oreville_wb.vlqeycb.omzomdl.ezgqrkb":{"initial_state":"ezgqrkb","states":{"ezgqrkb":{"animations":["omzomdl.ezgqrkb"],"transitions":[{"hykhqxz":"q.any_animation_finished"}]},"hykhqxz":{"animations":["omzomdl.hykhqxz"]}}},"controller.animation.oreville_wb.vlqeycb.omzomdl.open":{"initial_state":"open","states":{"open":{"animations":["omzomdl.open"],"transitions":[{"gsakhcn":"q.any_animation_finished"}]},"gsakhcn":{"animations":["omzomdl.gsakhcn"]}}}}}